[{"name":"Laptop","ProductPrice":"30000","ProductID":"1"},{"name":"Mobile Phone","ProductPrice":"10000","ProductID":"2"},{"name":"Computer","ProductPrice":"50000","ProductID":"3"},{"name":"Ladies Items","ProductPrice":"300","ProductID":"4"},{"name":"Gents","ProductPrice":"5000","ProductID":"5"},{"name":"Makeup Rpoducts","ProductPrice":"3000","ProductID":"6"},{"name":"Laptop","ProductPrice":"30000","ProductID":"7"},{"name":"Mobile Phone","ProductPrice":"10000","ProductID":"8"},{"name":"Computer","ProductPrice":"50000","ProductID":"9"},{"name":"Laptop","ProductPrice":"30000","ProductID":"10"},{"name":"Mobile Phone","ProductPrice":"10000","ProductID":"11"},{"name":"Computer","ProductPrice":"50000","ProductID":"12"}]